{
    "1": {
        "title": "Beto_Quintanilla_1",
        "link": "https://drive.google.com/file/d/17_vI22n4vwBOzY1IjsvSG6A6rBVUcVWY",
        "stream_name": "",
        "stream_key": "",
        "last_live": "",
        "schedule_time": ""
    },
    "2": {
        "title": "Beto_Quintanilla_2",
        "link": "https://drive.google.com/file/d/1x3qMQh60sSU8EOh6GwrqEBdWVFn4nG8z",
        "stream_name": "",
        "stream_key": "",
        "last_live": "",
        "schedule_time": ""
    },
    "3": {
        "title": "Beto_Quintanilla_3",
        "link": "https://drive.google.com/file/d/1PmtM0NM8R7Y-VnuEf-nQwp3TUAdUGaMJ",
        "stream_name": "",
        "stream_key": "",
        "last_live": "",
        "schedule_time": ""
    },
    "4": {
        "title": "Beto_Quintanilla_4",
        "link": "https://drive.google.com/file/d/1hf0tFwmoegD7mx9EblFN55Gw1WPDN92K",
        "stream_name": "",
        "stream_key": "",
        "last_live": "",
        "schedule_time": ""
    },
    "5": {
        "title": "Corridos Con Banda 1",
        "link": "https://drive.google.com/file/d/1FGIOfz2GMIDtrv4VYerz5PrYZq8VEUKZ",
        "stream_name": "",
        "stream_key": "",
        "last_live": "",
        "schedule_time": ""
    },
    "6": {
        "title": "Corridos Con Banda 2",
        "link": "https://drive.google.com/file/d/10w96nxlAuHmA59WXXF8jMK5huzYM8sc2",
        "stream_name": "",
        "stream_key": "",
        "last_live": "",
        "schedule_time": ""
    },
    "7": {
        "title": "Corridos Con Banda 3",
        "link": "https://drive.google.com/file/d/1Bw-smEm6QYh6oRMbjej7_biU4LSwQF4V",
        "stream_name": "",
        "stream_key": "",
        "last_live": "",
        "schedule_time": ""
    },
    "8": {
        "title": "Corridos Con Banda 4",
        "link": "https://drive.google.com/file/d/1RZy7jTv3X0UDnJdchDOSblbs-b9lasWT",
        "stream_name": "",
        "stream_key": "",
        "last_live": "",
        "schedule_time": ""
    },
    "9": {
        "title": "Corridos_Mix_1",
        "link": "https://drive.google.com/file/d/1gmvXrToNmMGrPGxaFAaWX3Mc3gHtvuZw",
        "stream_name": "",
        "stream_key": "",
        "last_live": "",
        "schedule_time": ""
    },
    "10": {
        "title": "Corridos_Mix_2",
        "link": "https://drive.google.com/file/d/1dPHRhjFezM2vKEeseiyJZisGhgtQiXmd",
        "stream_name": "",
        "stream_key": "",
        "last_live": "",
        "schedule_time": ""
    },
    "11": {
        "title": "Corridos_Mix_3",
        "link": "https://drive.google.com/file/d/1yAElPAa4OLh5bZCbHZbftowpFPxzQJpm",
        "stream_name": "",
        "stream_key": "",
        "last_live": "",
        "schedule_time": ""
    },
    "12": {
        "title": "Corridos_Mix_4",
        "link": "https://drive.google.com/file/d/1W05jeoUcURw236SDk-BMMSgm87NflTjU",
        "stream_name": "",
        "stream_key": "",
        "last_live": "",
        "schedule_time": ""
    },
    "13": {
        "title": "El_Tigrillo_1",
        "link": "https://drive.google.com/file/d/1OdvY8aRwtZpn_0VL92SdC4WXRARHBySi",
        "stream_name": "",
        "stream_key": "",
        "last_live": "",
        "schedule_time": ""
    },
    "14": {
        "title": "El_Tigrillo_2",
        "link": "https://drive.google.com/file/d/1dlBv9vt3PiDKBkGMLz9DotiaT0BwfhaW",
        "stream_name": "",
        "stream_key": "",
        "last_live": "",
        "schedule_time": ""
    },
    "15": {
        "title": "El_Tigrillo_3",
        "link": "https://drive.google.com/file/d/1-5iZ7W3bge92YpIs-iTrzsMgNsnB1rxu",
        "stream_name": "",
        "stream_key": "",
        "last_live": "",
        "schedule_time": ""
    },
    "16": {
        "title": "El_Tigrillo_4",
        "link": "https://drive.google.com/file/d/1zgN9Dam9yq57XURHJr81MODRbNH_TuAM",
        "stream_name": "",
        "stream_key": "",
        "last_live": "",
        "schedule_time": ""
    },
    "17": {
        "title": "Juan_Acuna_1",
        "link": "https://drive.google.com/file/d/1JfcfM09__Xp9reuln0TWXnsAvRmHgPhs",
        "stream_name": "",
        "stream_key": "",
        "last_live": "",
        "schedule_time": ""
    },
    "18": {
        "title": "Juan_Acuna_2",
        "link": "https://drive.google.com/file/d/1tPt7whZSbDsLqZpWVJTxNm9gM--L93TO",
        "stream_name": "",
        "stream_key": "",
        "last_live": "",
        "schedule_time": ""
    },
    "19": {
        "title": "Juan_Acuna_3",
        "link": "https://drive.google.com/file/d/1GNZg9gd6tzMzolv69PP4tbeQujwB16sx",
        "stream_name": "",
        "stream_key": "",
        "last_live": "",
        "schedule_time": ""
    },
    "20": {
        "title": "Juan_Acuna_4",
        "link": "https://drive.google.com/file/d/1y5QqcmLvENTuTHWFMrQYhvJMvOtycP2s",
        "stream_name": "",
        "stream_key": "",
        "last_live": "",
        "schedule_time": ""
    }
}